mixture_density_nets/__init__.py
mixture_density_nets/mdn.py
Mixture_Density_Nets-0.1.1.dist-info/LICENSE
Mixture_Density_Nets-0.1.1.dist-info/METADATA
Mixture_Density_Nets-0.1.1.dist-info/WHEEL
Mixture_Density_Nets-0.1.1.dist-info/top_level.txt
Mixture_Density_Nets-0.1.1.dist-info/RECORD
