Metadata-Version: 2.1
Name: Mixture-Density-Nets
Version: 0.1.1
Summary: A small PyTorch library for Mixture Density Networks.
Home-page: https://github.com/romue404/mixture-density-nets
Author: Robert Müller
Author-email: robert.mueller1990@googlemail.com
License: MIT
Keywords: artificial intelligence,pytorch,mixture density network
Classifier: Development Status :: 4 - Beta
Classifier: Intended Audience :: Developers
Classifier: Topic :: Scientific/Engineering :: Artificial Intelligence
Classifier: License :: OSI Approved :: MIT License
Classifier: Programming Language :: Python :: 3.6
License-File: LICENSE
Requires-Dist: torch >=1.6
Requires-Dist: numpy
